yahoofantasy/__init__.py
yahoofantasy/context.py
yahoofantasy/api/__init__.py
yahoofantasy/api/attr.py
yahoofantasy/api/fetch.py
yahoofantasy/api/games.py
yahoofantasy/api/parse.py
yahoofantasy/api/tests/__init__.py
yahoofantasy/api/tests/test_parse.py
yahoofantasy/api/tests/sample_data/example.xml
yahoofantasy/cli/__init__.py
yahoofantasy/cli/clear_cache.py
yahoofantasy/cli/dump.py
yahoofantasy/cli/localhost-key.pem
yahoofantasy/cli/localhost.pem
yahoofantasy/cli/login.py
yahoofantasy/cli/shell.py
yahoofantasy/cli/utils.py
yahoofantasy/resources/__init__.py
yahoofantasy/resources/draft_result.py
yahoofantasy/resources/league.py
yahoofantasy/resources/matchup.py
yahoofantasy/resources/player.py
yahoofantasy/resources/roster.py
yahoofantasy/resources/standings.py
yahoofantasy/resources/team.py
yahoofantasy/resources/transaction.py
yahoofantasy/resources/week.py
yahoofantasy/stats/__init__.py
yahoofantasy/stats/generate.py
yahoofantasy/stats/mlb.py
yahoofantasy/stats/nba.py
yahoofantasy/stats/nfl.py
yahoofantasy/stats/nhl.py
yahoofantasy/stats/stat.py
yahoofantasy/stats/utils.py
yahoofantasy/stats/tests/__init__.py
yahoofantasy/stats/tests/test_utils.py
yahoofantasy/util/__init__.py
yahoofantasy/util/logger.py
yahoofantasy/util/persistence.py
yahoofantasy/util/tests/__init__.py
yahoofantasy/util/tests/test_persistence.py
yahoofantasy-1.4.9.dist-info/METADATA
yahoofantasy-1.4.9.dist-info/WHEEL
yahoofantasy-1.4.9.dist-info/entry_points.txt
yahoofantasy-1.4.9.dist-info/top_level.txt
yahoofantasy-1.4.9.dist-info/RECORD
