Metadata-Version: 2.4
Name: yahoofantasy
Version: 1.4.9
Summary: An SDK for the Yahoo! Fantasy Sports API
Home-page: https://github.com/mattdodge/yahoofantasy
Author: Matt Dodge
Author-email: matt@dodge.com
Classifier: Programming Language :: Python :: 3
Classifier: License :: OSI Approved :: MIT License
Classifier: Operating System :: OS Independent
Requires-Dist: click
Requires-Dist: colorama
Requires-Dist: requests
Requires-Dist: pydash
Requires-Dist: xmljson
Dynamic: author
Dynamic: author-email
Dynamic: classifier
Dynamic: description
Dynamic: description-content-type
Dynamic: home-page
Dynamic: requires-dist
Dynamic: summary
